nonebot_plugin_helloworld/__init__.py
nonebot_plugin_helloworld-0.2.0.dist-info/WHEEL
nonebot_plugin_helloworld-0.2.0.dist-info/METADATA
nonebot_plugin_helloworld-0.2.0.dist-info/licenses/LICENSE
nonebot_plugin_helloworld-0.2.0.dist-info/RECORD
