Metadata-Version: 2.1
Name: nonebot-plugin-helloworld
Version: 0.2.0
Summary: NoneBot2 Hello World
License: MIT
Author-email: Akirami <Akiramiaya@outlook.com>
Requires-Python: >=3.8
Requires-Dist: nonebot2>=2.0.0rc3
Project-URL: Homepage, https://github.com/A-kirami/nonebot-plugin-helloworld
Project-URL: Repository, https://github.com/A-kirami/nonebot-plugin-helloworld
